test/__init__.py
test/test_multithreading.py
test/collections/__init__.py
test/collections/test_dict_access.py
test/collections/test_safe_dict.py
wmeijer_utils/__init__.py
wmeijer_utils/file.py
wmeijer_utils/general.py
wmeijer_utils/iterators.py
wmeijer_utils/json.py
wmeijer_utils/multithreading.py
wmeijer_utils/regex.py
wmeijer_utils/collections/__init__.py
wmeijer_utils/collections/dict_access.py
wmeijer_utils/collections/list_access.py
wmeijer_utils/collections/safe_dict.py
wmeijer_utils/pandas/__init__.py
wmeijer_utils/pandas/dataframe.py
wmeijer_utils/pandas/transforms.py
wmeijer_utils/pandas/figures/__init__.py
wmeijer_utils/pandas/figures/base.py
wmeijer_utils/pandas/figures/plots.py
wmeijer_utils/pandas/figures/pretty_plots.py
wmeijer_utils-0.10.0.dist-info/LICENSE
wmeijer_utils-0.10.0.dist-info/METADATA
wmeijer_utils-0.10.0.dist-info/WHEEL
wmeijer_utils-0.10.0.dist-info/top_level.txt
wmeijer_utils-0.10.0.dist-info/RECORD
