Metadata-Version: 2.1
Name: wmeijer_utils
Version: 0.10.0
Summary: Contains a diverse set of utility methods I use in Python.
Home-page: https://github.com/wmeijer221/my_python_utils
Author: Willem Meijer
Author-email: wmeijer221 <me@wmeijer.com>
License: MIT License
Project-URL: repository, https://github.com/wmeijer221/my_python_utils
Classifier: Programming Language :: Python :: 3
Classifier: License :: OSI Approved :: MIT License
Classifier: Operating System :: OS Independent
Requires-Python: >=3.6
License-File: LICENSE
